Metadata-Version: 2.1
Name: pypi-python-translator
Version: 2.5.2
Summary: A Python package for translation
Home-page: https://github.com/SForces/pypi_python_translator
Author: SForces
Author-email: osmntn08@gmail.com
Classifier: Programming Language :: Python :: 3
Classifier: License :: OSI Approved :: MIT License
Classifier: Operating System :: OS Independent
Requires-Python: >=3.6
